README.md
license.txt
pyproject.toml
setup.cfg
setup.py
szzlearning/__init__.py
szzlearning/sklearns.py
szzlearning.egg-info/PKG-INFO
szzlearning.egg-info/SOURCES.txt
szzlearning.egg-info/dependency_links.txt
szzlearning.egg-info/top_level.txt