Metadata-Version: 2.1
Name: szzlearning
Version: 0.0.1
Summary: Description's package
Author: Author's name
License-File: license.txt
